{
  "project_info": {
    "project_number": "89696123358",
    "firebase_url": "https://audientes-298fb.firebaseio.com",
    "project_id": "audientes-298fb",
    "storage_bucket": "audientes-298fb.appspot.com"
  },
  "client": [
    {
      "client_info": {
        "mobilesdk_app_id": "1:89696123358:android:78f0292d8d47b1686b454f",
        "android_client_info": {
          "package_name": "com.example.audientes"
        }
      },
      "oauth_client": [
        {
          "client_id": "89696123358-v6aoi7e7upkdop4al78usfnc2s8n85n6.apps.googleusercontent.com",
          "client_type": 3
        }
      ],
      "api_key": [
        {
          "current_key": "AIzaSyDdraPQCPPGT6KAaBWYArJdRYKBAArcdJE"
        }
      ],
      "services": {
        "appinvite_service": {
          "other_platform_oauth_client": [
            {
              "client_id": "89696123358-v6aoi7e7upkdop4al78usfnc2s8n85n6.apps.googleusercontent.com",
              "client_type": 3
            }
          ]
        }
      }
    }
  ],
  "configuration_version": "1"
}